tomtag.cp310-win_amd64.pyd
tomtag/correlation.c
tomtag/correlation.h
tomtag/correlation_module.c
tomtag/correlation_module.pyi
tomtag-0.13.dist-info/LICENSE
tomtag-0.13.dist-info/METADATA
tomtag-0.13.dist-info/WHEEL
tomtag-0.13.dist-info/top_level.txt
tomtag-0.13.dist-info/RECORD
