Metadata-Version: 2.1
Name: tomtag
Version: 0.13
Summary: Package to identify correlated single photon detection events.
Author-email: Thomas Jaeken <tj2022@hw.ac.uk>
License: MIT License
Project-URL: Homepage, https://github.com/Thomas-Jaeken/tomtag
Project-URL: Documentation, https://tomtag.readthedocs.io
Project-URL: Repository, https://github.com/Thomas-Jaeken/tomtag.git
Project-URL: Bug Tracker, https://github.com/Thomas-Jaeken/tomtag/issues
Keywords: timetag
Classifier: Programming Language :: Python :: 3
Classifier: License :: OSI Approved :: MIT License
Classifier: Operating System :: OS Independent
Requires-Python: >=3.8
License-File: LICENSE
Requires-Dist: numpy
